setup.cfg
setup.py
secure_graphene/__init__.py
secure_graphene/depth.py
secure_graphene.egg-info/PKG-INFO
secure_graphene.egg-info/SOURCES.txt
secure_graphene.egg-info/dependency_links.txt
secure_graphene.egg-info/requires.txt
secure_graphene.egg-info/top_level.txt