Metadata-Version: 1.1
Name: secure-graphene
Version: 0.1.2
Summary: Python library that assists you in securing your GraphQL API against malicious queries
Home-page: https://github.com/manesioz/secure-graphene
Author: Zachary Manesiotis
Author-email: zack.manesiotis@gmail.com
License: MIT
Download-URL: https://github.com/manesioz/secure-graphene/archive/v0.1.2.tar.gz
Keywords: graphql,python,security,graphene,api
Platform: UNKNOWN
Classifier: Development Status :: 3 - Alpha
Classifier: Intended Audience :: Developers
Classifier: Topic :: Software Development :: Build Tools
Classifier: License :: OSI Approved :: MIT License
Classifier: Programming Language :: Python :: 3
Classifier: Programming Language :: Python :: 3.4
Classifier: Programming Language :: Python :: 3.5
Classifier: Programming Language :: Python :: 3.6
